{
  "required": true,
  "package": "kaptainwutax.playback.mixin",
  "compatibilityLevel": "JAVA_8",
  "mixins": [
    "network.ClientConnectionMixin",
    "server.world.ChunkTicketManagerMixin",
    "network.packet.s2c.play.EntitySpawnS2CPacketMixin",
    "server.MinecraftServerMixin",
    "network.NetworkThreadUtilsMixin",
    "server.world.ServerChunkManagerMixin",
    "server.network.ServerPlayNetworkHandlerMixin"
  ],
  "client": [
    "client.network.ClientPlayerEntityMixin",
    "client.network.ClientPlayerInteractionManagerMixin",
    "client.network.ClientPlayNetworkHandlerMixin",
    "client.world.ClientWorldMixin",
    "client.util.InputUtilMixin",
    "client.options.KeyBindingMixin",
    "client.KeyboardMixin",
    "client.input.KeyboardInputMixin",
    "client.MinecraftClientMixin",
    "client.MouseMixin",
    "client.gui.screen.TitleScreenMixin",
    "client.render.MinecraftClient_Render_Mixin",
    "client.render.RenderTickCounterMixin",
    "client.render.WorldRendererMixin",
    "client.sound.PositionedSoundInstanceMixin"
  ],
  "injectors": {
    "defaultRequire": 1
  }
}
